SQLHelpersAJM/__init__.py
SQLHelpersAJM/_version.py
SQLHelpersAJM/backend/__init__.py
SQLHelpersAJM/backend/errors.py
SQLHelpersAJM/backend/meta.py
SQLHelpersAJM/helpers/__init__.py
SQLHelpersAJM/helpers/bases.py
SQLHelpersAJM/helpers/postgres.py
SQLHelpersAJM/helpers/sql_server.py
SQLHelpersAJM/helpers/sqlite3_helper.py
sqlhelpersajm-0.4.2.dist-info/licenses/LICENSE.txt
sqlhelpersajm-0.4.2.dist-info/METADATA
sqlhelpersajm-0.4.2.dist-info/WHEEL
sqlhelpersajm-0.4.2.dist-info/top_level.txt
sqlhelpersajm-0.4.2.dist-info/RECORD
