Metadata-Version: 2.4
Name: SQLHelpersAJM
Version: 0.4.2
Summary: classes meant to streamline interaction with multiple different flavors of SQL database
Home-page: https://github.com/amcsparron2793-Water/SQLHelpersAJM
Download-URL: https://github.com/amcsparron2793-Water/SQLHelpersAJM/archive/refs/tags/0.4.2.tar.gz
Author: Amcsparron
Author-email: amcsparron@albanyny.gov
License: MIT License
Classifier: Development Status :: 4 - Beta
Classifier: Intended Audience :: Developers
Classifier: Topic :: Software Development :: Build Tools
Classifier: License :: OSI Approved :: MIT License
Classifier: Programming Language :: Python :: 3
License-File: LICENSE.txt
Dynamic: author
Dynamic: author-email
Dynamic: classifier
Dynamic: description
Dynamic: description-content-type
Dynamic: download-url
Dynamic: home-page
Dynamic: license
Dynamic: license-file
Dynamic: summary
